mpcd/__init__.py
mpcd/grouper.py
mpcd/mpcd.py
mpcd/visualizer.py
mpcd/tests/__init__.py
mpcd-0.1.1.dist-info/LICENSE
mpcd-0.1.1.dist-info/METADATA
mpcd-0.1.1.dist-info/WHEEL
mpcd-0.1.1.dist-info/top_level.txt
mpcd-0.1.1.dist-info/RECORD
