Metadata-Version: 2.1
Name: mpcd
Version: 0.1.1
Summary: Pure Python PCD reader/writer
Author-email: Yuehao Wang <mail@yuehao.wang>
Project-URL: Homepage, https://github.com/BossaMelon/mpcd
Project-URL: Bug Tracker, https://github.com/BossaMelon/mpcd/issues
Classifier: Programming Language :: Python :: 3
Classifier: License :: OSI Approved :: MIT License
Classifier: Operating System :: OS Independent
Requires-Python: >=3.7
License-File: LICENSE
Requires-Dist: numpy
Requires-Dist: python-lzf
Requires-Dist: Pillow
Requires-Dist: opencv-python
Requires-Dist: tqdm
